sparksneeze/__init__.py
sparksneeze/cli.py
sparksneeze/core.py
sparksneeze/enums.py
sparksneeze/py.typed
sparksneeze/spark_utils.py
sparksneeze/data_sources/__init__.py
sparksneeze/data_sources/base.py
sparksneeze/data_sources/dataframe.py
sparksneeze/data_sources/path.py
sparksneeze/data_sources/table.py
sparksneeze/data_targets/__init__.py
sparksneeze/data_targets/base.py
sparksneeze/data_targets/delta.py
sparksneeze/logging/__init__.py
sparksneeze/logging/logger.py
sparksneeze/metadata/__init__.py
sparksneeze/metadata/applier.py
sparksneeze/metadata/config.py
sparksneeze/metadata/utils.py
sparksneeze/schema_evolution/__init__.py
sparksneeze/schema_evolution/dataframe_aligner.py
sparksneeze/schema_evolution/evolution_handler.py
sparksneeze/schema_evolution/evolution_metadata.py
sparksneeze/schema_evolution/type_compatibility.py
sparksneeze/strategy/__init__.py
sparksneeze/strategy/append.py
sparksneeze/strategy/base.py
sparksneeze/strategy/drop_create.py
sparksneeze/strategy/historize.py
sparksneeze/strategy/truncate.py
sparksneeze/strategy/upsert.py
sparksneeze-0.1.4.dist-info/METADATA
sparksneeze-0.1.4.dist-info/WHEEL
sparksneeze-0.1.4.dist-info/entry_points.txt
sparksneeze-0.1.4.dist-info/licenses/LICENSE
sparksneeze-0.1.4.dist-info/RECORD
