Metadata-Version: 2.4
Name: sparksneeze
Version: 0.1.4
Summary: Strategy-based data warehouse transformations using Apache Spark with automatic metadata enrichment and schema evolution
Project-URL: Homepage, https://github.com/mdouwes/sparksneeze
Project-URL: Repository, https://github.com/mdouwes/sparksneeze
Project-URL: Issues, https://github.com/mdouwes/sparksneeze/issues
Author-email: Merijn Douwes <merijn@douwes.me>
License-File: LICENSE
Requires-Python: >=3.9.0
Requires-Dist: delta-spark==4.0.0
Requires-Dist: pyspark==4.0.0
Requires-Dist: structlog>=24.0.0
Provides-Extra: dev
Requires-Dist: black; extra == 'dev'
Requires-Dist: doc8; extra == 'dev'
Requires-Dist: myst-parser; extra == 'dev'
Requires-Dist: pytest-cov>=6.1.1; extra == 'dev'
Requires-Dist: pytest>=8.4.0; extra == 'dev'
Requires-Dist: ruff; extra == 'dev'
Requires-Dist: sphinx-design; extra == 'dev'
Requires-Dist: sphinx-rtd-theme; extra == 'dev'
Requires-Dist: sphinx>=5.0; extra == 'dev'
Requires-Dist: ty; extra == 'dev'
Requires-Dist: vulture; extra == 'dev'
Provides-Extra: docs
Requires-Dist: doc8; extra == 'docs'
Requires-Dist: myst-parser; extra == 'docs'
Requires-Dist: sphinx-design; extra == 'docs'
Requires-Dist: sphinx-rtd-theme; extra == 'docs'
Requires-Dist: sphinx>=5.0; extra == 'docs'
Provides-Extra: test
Requires-Dist: pytest-cov>=6.1.1; extra == 'test'
Requires-Dist: pytest>=8.4.0; extra == 'test'
